{
  "Antares": "v0.7.30",
  "Beancount": "3.0.0",
  "Celery": "5.4.0",
  "YOURLS": "1.9.2",
  "ansible": "11.1.0",
  "ansible-semaphore": "v2.11.2",
  "argocd": "v2.13.3",
  "balena-engine": "v20.10.44",
  "bat": "v0.25.0",
  "bazarr": "v1.5.1",
  "bitwarden-desktop": "v2022.5.1",
  "bitwarden-mobile": "v2024.10.0",
  "borgbackup": "1.4.0",
  "bottom": "0.10.2",
  "buildah": "v1.38.0",
  "compose": "v2.32.2",
  "django": "5.1.4",
  "docker-cli": "v27.5.0-rc.2",
  "docker-pi-hole": "2024.07.0",
  "fd": "v10.2.0",
  "flaresolverr": "v3.3.21",
  "flask": "3.1.0",
  "fzf": "v0.57.0",
  "gitlab-ci-local": "4.56.2",
  "gotify": "v2.6.1",
  "grafana": "v11.4.0",
  "hatch": "hatch-v1.14.0",
  "headscale": "v0.23.0",
  "homarr": "v0.15.10",
  "insomnia": "core@10.3.0",
  "jellyfin-media-player": "v1.11.1",
  "jellyseerr": "v2.2.3",
  "jq": "jq-1.7.1",
  "kombu": "5.4.2",
  "metallb": "v0.14.9",
  "nala": "v0.15.4",
  "nvchecker": "v2.16",
  "pi-hole": "v5.18.4",
  "podman": "v5.3.1",
  "prometheus": "v3.1.0",
  "prometheus-blackbox_exporter": "v0.25.0",
  "prometheus-node_exporter": "v1.8.2",
  "prowlarr": "v1.29.2.4915",
  "pulumi": "v3.145.0",
  "pyinfra": "v3.2",
  "radarr": "v5.17.2.9580",
  "sentry": "24.12.1",
  "skopeo": "v1.17.0",
  "sonarr": "v4.0.12.2823",
  "speedtest-tracker": "v1.0.3",
  "terraform": "v1.10.4",
  "tornado": "6.4.2",
  "umami": "v2.15.1",
  "uptime-kuma": "1.23.16",
  "vaultwarden": "1.32.7",
  "vscodium": "1.96.2.24355",
  "webhook": "2.8.2",
  "woodpecker-ci": "v2.8.2",
  "youtube-dl": "2021.12.17",
  "zoxide": "v0.9.6",
  "zsh": "5.4.1"
}
